httpie_edgegrid.py
httpie_edgegrid-2.2.4.dist-info/licenses/LICENSE
httpie_edgegrid-2.2.4.dist-info/METADATA
httpie_edgegrid-2.2.4.dist-info/WHEEL
httpie_edgegrid-2.2.4.dist-info/entry_points.txt
httpie_edgegrid-2.2.4.dist-info/top_level.txt
httpie_edgegrid-2.2.4.dist-info/RECORD
