Metadata-Version: 2.4
Name: httpie-edgegrid
Version: 2.2.4
Summary: Edgegrid plugin for HTTPie.
Home-page: https://github.com/akamai/httpie-edgegrid
Download-URL: https://github.com/akamai/httpie-edgegrid
License: Apache 2.0
Requires-Python: >=3.9
License-File: LICENSE
Requires-Dist: httpie>=3.0.0
Requires-Dist: edgegrid-python>=2.0.4
Provides-Extra: dev
Requires-Dist: pylint>=2.15.0; extra == "dev"
Requires-Dist: pytest>=7.0.0; extra == "dev"
Requires-Dist: pytest-cov>=4.0.0; extra == "dev"
Dynamic: description
Dynamic: description-content-type
Dynamic: download-url
Dynamic: home-page
Dynamic: license
Dynamic: license-file
Dynamic: provides-extra
Dynamic: requires-dist
Dynamic: requires-python
Dynamic: summary
